primalschemers-0.1.12.dist-info/METADATA
primalschemers-0.1.12.dist-info/WHEEL
primalschemers-0.1.12.dist-info/licenses/LICENSE
primalschemers/__init__.py
primalschemers/primalschemers.cpython-310-powerpc64le-linux-gnu.so
primalschemers-0.1.12.dist-info/RECORD
