Metadata-Version: 2.4
Name: primalschemers
Version: 0.1.12
Classifier: Programming Language :: Rust
Classifier: Programming Language :: Python :: Implementation :: CPython
Classifier: Programming Language :: Python :: Implementation :: PyPy
License-File: LICENSE
Summary: Rust code base for PrimalScheme3
Author-email: ChrisKent <chrisgkent@protonmail.com>
License-Expression: GPL-3.0-only
Requires-Python: >=3.10
